{
  "matches": [
    {
      "src": "name: sorted_data [100,111]",
      "dest": "name: sorted_data [392,403]"
    },
    {
      "src": "trailer [72,78]",
      "dest": "trailer [364,370]"
    },
    {
      "src": "name: median [251,257]",
      "dest": "name: median [543,549]"
    },
    {
      "src": "expr_stmt [52,78]",
      "dest": "expr_stmt [344,370]"
    },
    {
      "src": "suite [21,375]",
      "dest": "suite [21,667]"
    },
    {
      "src": "name: DataStatistics [6,20]",
      "dest": "name: DataStatistics [6,20]"
    },
    {
      "src": "simple_stmt [200,239]",
      "dest": "simple_stmt [492,531]"
    },
    {
      "src": "number: 2 [133,134]",
      "dest": "number: 2 [425,426]"
    },
    {
      "src": "classdef [0,375]",
      "dest": "classdef [0,667]"
    },
    {
      "src": "suite [43,375]",
      "dest": "suite [49,667]"
    },
    {
      "src": "atom_expr [319,343]",
      "dest": "atom_expr [611,635]"
    },
    {
      "src": "simple_stmt [251,284]",
      "dest": "simple_stmt [543,576]"
    },
    {
      "src": "trailer [221,238]",
      "dest": "trailer [513,530]"
    },
    {
      "src": "expr_stmt [310,343]",
      "dest": "expr_stmt [602,635]"
    },
    {
      "src": "suite [140,284]",
      "dest": "suite [432,576]"
    },
    {
      "src": "operator: = [161,162]",
      "dest": "operator: = [453,454]"
    },
    {
      "src": "atom [260,279]",
      "dest": "atom [552,571]"
    },
    {
      "src": "operator: = [94,95]",
      "dest": "operator: = [386,387]"
    },
    {
      "src": "simple_stmt [310,344]",
      "dest": "simple_stmt [602,636]"
    },
    {
      "src": "number: 2 [232,233]",
      "dest": "number: 2 [524,525]"
    },
    {
      "src": "arith_expr [261,278]",
      "dest": "arith_expr [553,570]"
    },
    {
      "src": "simple_stmt [87,113]",
      "dest": "simple_stmt [379,405]"
    },
    {
      "src": "term [175,186]",
      "dest": "term [467,478]"
    },
    {
      "src": "return_stmt [352,375]",
      "dest": "return_stmt [644,667]"
    },
    {
      "src": "operator: // [182,184]",
      "dest": "operator: // [474,476]"
    },
    {
      "src": "trailer [364,375]",
      "dest": "trailer [656,667]"
    },
    {
      "src": "name: median2 [200,207]",
      "dest": "name: median2 [492,499]"
    },
    {
      "src": "name: sorted_data [52,63]",
      "dest": "name: sorted_data [344,355]"
    },
    {
      "src": "name: median [365,371]",
      "dest": "name: median [657,663]"
    },
    {
      "src": "name: sorted [66,72]",
      "dest": "name: sorted [358,364]"
    },
    {
      "src": "term [331,342]",
      "dest": "term [623,634]"
    },
    {
      "src": "name: median1 [153,160]",
      "dest": "name: median1 [445,452]"
    },
    {
      "src": "operator: , [371,372]",
      "dest": "operator: , [663,664]"
    },
    {
      "src": "simple_stmt [52,79]",
      "dest": "simple_stmt [344,371]"
    },
    {
      "src": "expr_stmt [200,238]",
      "dest": "expr_stmt [492,530]"
    },
    {
      "src": "expr_stmt [251,283]",
      "dest": "expr_stmt [543,575]"
    },
    {
      "src": "name: length [124,130]",
      "dest": "name: length [416,422]"
    },
    {
      "src": "name: sorted_data [319,330]",
      "dest": "name: sorted_data [611,622]"
    },
    {
      "src": "atom_expr [66,78]",
      "dest": "atom_expr [358,370]"
    },
    {
      "src": "operator: = [317,318]",
      "dest": "operator: = [609,610]"
    },
    {
      "src": "operator: = [64,65]",
      "dest": "operator: = [356,357]"
    },
    {
      "src": "funcdef [26,375]",
      "dest": "funcdef [26,667]"
    },
    {
      "src": "suite [297,344]",
      "dest": "suite [589,636]"
    },
    {
      "src": "arith_expr [222,237]",
      "dest": "arith_expr [514,529]"
    },
    {
      "src": "parameters [36,42]",
      "dest": "parameters [36,48]"
    },
    {
      "src": "name: median [30,36]",
      "dest": "name: median [30,36]"
    },
    {
      "src": "operator: = [258,259]",
      "dest": "operator: = [550,551]"
    },
    {
      "src": "number: 2 [341,342]",
      "dest": "number: 2 [633,634]"
    },
    {
      "src": "name: length [175,181]",
      "dest": "name: length [467,473]"
    },
    {
      "src": "comparison [124,139]",
      "dest": "comparison [416,431]"
    },
    {
      "src": "simple_stmt [153,188]",
      "dest": "simple_stmt [445,480]"
    },
    {
      "src": "name: sorted_data [210,221]",
      "dest": "name: sorted_data [502,513]"
    },
    {
      "src": "operator: == [135,137]",
      "dest": "operator: == [427,429]"
    },
    {
      "src": "number: 2 [282,283]",
      "dest": "number: 2 [574,575]"
    },
    {
      "src": "atom_expr [359,375]",
      "dest": "atom_expr [651,667]"
    },
    {
      "src": "number: 1 [236,237]",
      "dest": "number: 1 [528,529]"
    },
    {
      "src": "number: 2 [373,374]",
      "dest": "number: 2 [665,666]"
    },
    {
      "src": "operator: // [338,340]",
      "dest": "operator: // [630,632]"
    },
    {
      "src": "term [124,134]",
      "dest": "term [416,426]"
    },
    {
      "src": "operator: % [131,132]",
      "dest": "operator: % [423,424]"
    },
    {
      "src": "name: len [96,99]",
      "dest": "name: len [388,391]"
    },
    {
      "src": "arglist [365,374]",
      "dest": "arglist [657,666]"
    },
    {
      "src": "name: data [37,41]",
      "dest": "name: data [43,47]"
    },
    {
      "src": "name: length [331,337]",
      "dest": "name: length [623,629]"
    },
    {
      "src": "file_input [0,375]",
      "dest": "file_input [0,667]"
    },
    {
      "src": "number: 2 [185,186]",
      "dest": "number: 2 [477,478]"
    },
    {
      "src": "name: median2 [271,278]",
      "dest": "name: median2 [563,570]"
    },
    {
      "src": "expr_stmt [87,112]",
      "dest": "expr_stmt [379,404]"
    },
    {
      "src": "atom_expr [163,187]",
      "dest": "atom_expr [455,479]"
    },
    {
      "src": "operator: = [208,209]",
      "dest": "operator: = [500,501]"
    },
    {
      "src": "name: data [73,77]",
      "dest": "name: data [365,369]"
    },
    {
      "src": "number: 0 [138,139]",
      "dest": "number: 0 [430,431]"
    },
    {
      "src": "atom_expr [96,112]",
      "dest": "atom_expr [388,404]"
    },
    {
      "src": "trailer [99,112]",
      "dest": "trailer [391,404]"
    },
    {
      "src": "name: round [359,364]",
      "dest": "name: round [651,656]"
    },
    {
      "src": "trailer [174,187]",
      "dest": "trailer [466,479]"
    },
    {
      "src": "name: median1 [261,268]",
      "dest": "name: median1 [553,560]"
    },
    {
      "src": "name: sorted_data [163,174]",
      "dest": "name: sorted_data [455,466]"
    },
    {
      "src": "expr_stmt [153,187]",
      "dest": "expr_stmt [445,479]"
    },
    {
      "src": "operator: - [234,235]",
      "dest": "operator: - [526,527]"
    },
    {
      "src": "term [260,283]",
      "dest": "term [552,575]"
    },
    {
      "src": "atom_expr [210,238]",
      "dest": "atom_expr [502,530]"
    },
    {
      "src": "operator: / [280,281]",
      "dest": "operator: / [572,573]"
    },
    {
      "src": "param [37,41]",
      "dest": "param [43,47]"
    },
    {
      "src": "term [222,233]",
      "dest": "term [514,525]"
    },
    {
      "src": "if_stmt [121,344]",
      "dest": "if_stmt [413,636]"
    },
    {
      "src": "name: median [310,316]",
      "dest": "name: median [602,608]"
    },
    {
      "src": "name: length [222,228]",
      "dest": "name: length [514,520]"
    },
    {
      "src": "operator: // [229,231]",
      "dest": "operator: // [521,523]"
    },
    {
      "src": "operator: + [269,270]",
      "dest": "operator: + [561,562]"
    },
    {
      "src": "trailer [330,343]",
      "dest": "trailer [622,635]"
    },
    {
      "src": "name: length [87,93]",
      "dest": "name: length [379,385]"
    }
  ],
  "actions": [
    {
      "action": "insert-tree",
      "tree": "param [37,42]",
      "parent": "parameters [36,48]",
      "at": 0
    },
    {
      "action": "insert-tree",
      "tree": "simple_stmt [58,336]",
      "parent": "suite [49,667]",
      "at": 0
    }
  ]
}