{
  "matches": [
    {
      "src": "expr_stmt [105,186]",
      "dest": "expr_stmt [116,223]"
    },
    {
      "src": "param [41,47]",
      "dest": "param [47,58]"
    },
    {
      "src": "trailer [692,695]",
      "dest": "trailer [596,599]"
    },
    {
      "src": "name: lower [132,137]",
      "dest": "name: lower [143,148]"
    },
    {
      "src": "name: process [33,40]",
      "dest": "name: process [33,40]"
    },
    {
      "src": "suite [24,757]",
      "dest": "suite [24,741]"
    },
    {
      "src": "operator: = [120,121]",
      "dest": "operator: = [131,132]"
    },
    {
      "src": "sync_comp_for [140,185]",
      "dest": "sync_comp_for [177,222]"
    },
    {
      "src": "argument [677,695]",
      "dest": "argument [581,599]"
    },
    {
      "src": "classdef [0,757]",
      "dest": "classdef [0,741]"
    },
    {
      "src": "atom_expr [691,695]",
      "dest": "atom_expr [595,599]"
    },
    {
      "src": "suite [49,757]",
      "dest": "suite [60,741]"
    },
    {
      "src": "name: c [174,175]",
      "dest": "name: c [211,212]"
    },
    {
      "src": "atom_expr [122,186]",
      "dest": "atom_expr [133,223]"
    },
    {
      "src": "name: isalpha [161,168]",
      "dest": "name: isalpha [198,205]"
    },
    {
      "src": "operator: = [354,355]",
      "dest": "operator: = [391,392]"
    },
    {
      "src": "trailer [278,284]",
      "dest": "trailer [315,321]"
    },
    {
      "src": "lambdef [681,695]",
      "dest": "lambdef [585,599]"
    },
    {
      "src": "trailer [160,168]",
      "dest": "trailer [197,205]"
    },
    {
      "src": "trailer [124,129]",
      "dest": "trailer [135,140]"
    },
    {
      "src": "name: word_list [252,261]",
      "dest": "name: word_list [289,298]"
    },
    {
      "src": "argument [697,709]",
      "dest": "argument [601,613]"
    },
    {
      "src": "name: word_frequency [653,667]",
      "dest": "name: word_frequency [557,571]"
    },
    {
      "src": "name: x [688,689]",
      "dest": "name: x [592,593]"
    },
    {
      "src": "param [688,689]",
      "dest": "param [592,593]"
    },
    {
      "src": "trailer [137,139]",
      "dest": "trailer [148,150]"
    },
    {
      "src": "atom_expr [646,710]",
      "dest": "atom_expr [550,614]"
    },
    {
      "src": "trailer [459,465]",
      "dest": "trailer [397,422]"
    },
    {
      "src": "parameters [40,48]",
      "dest": "parameters [40,59]"
    },
    {
      "src": "trailer [183,185]",
      "dest": "trailer [220,222]"
    },
    {
      "src": "name: c [130,131]",
      "dest": "name: c [141,142]"
    },
    {
      "src": "name: key [677,680]",
      "dest": "name: key [581,584]"
    },
    {
      "src": "expr_stmt [252,286]",
      "dest": "expr_stmt [289,323]"
    },
    {
      "src": "atom_expr [641,711]",
      "dest": "atom_expr [545,615]"
    },
    {
      "src": "operator: = [680,681]",
      "dest": "operator: = [584,585]"
    },
    {
      "src": "trailer [129,186]",
      "dest": "trailer [140,223]"
    },
    {
      "src": "name: word [460,464]",
      "dest": "name: calculate_word_frequency [398,422]"
    },
    {
      "src": "operator: , [695,696]",
      "dest": "operator: , [599,600]"
    },
    {
      "src": "trailer [175,183]",
      "dest": "trailer [212,220]"
    },
    {
      "src": "atom_expr [174,185]",
      "dest": "atom_expr [211,222]"
    },
    {
      "src": "return_stmt [729,757]",
      "dest": "return_stmt [682,740]"
    },
    {
      "src": "funcdef [29,757]",
      "dest": "funcdef [29,741]"
    },
    {
      "src": "name: c [159,160]",
      "dest": "name: c [196,197]"
    },
    {
      "src": "expr_stmt [617,711]",
      "dest": "expr_stmt [521,615]"
    },
    {
      "src": "operator: , [675,676]",
      "dest": "operator: , [579,580]"
    },
    {
      "src": "name: join [125,129]",
      "dest": "name: join [136,140]"
    },
    {
      "src": "name: sorted [646,652]",
      "dest": "name: sorted [550,556]"
    },
    {
      "src": "name: string [41,47]",
      "dest": "name: string_list [47,58]"
    },
    {
      "src": "trailer [667,673]",
      "dest": "trailer [571,577]"
    },
    {
      "src": "number: 1 [693,694]",
      "dest": "number: 1 [597,598]"
    },
    {
      "src": "name: sorted_word_frequency [617,638]",
      "dest": "name: sorted_word_frequency [521,542]"
    },
    {
      "src": "atom_expr [653,675]",
      "dest": "atom_expr [557,579]"
    },
    {
      "src": "atom_expr [159,170]",
      "dest": "atom_expr [196,207]"
    },
    {
      "src": "trailer [673,675]",
      "dest": "trailer [577,579]"
    },
    {
      "src": "trailer [131,137]",
      "dest": "trailer [142,148]"
    },
    {
      "src": "name: NLPDataProcessor2 [6,23]",
      "dest": "name: NLPDataProcessor2 [6,23]"
    },
    {
      "src": "argument [130,185]",
      "dest": "argument [141,222]"
    },
    {
      "src": "name: word [371,375]",
      "dest": "name: self [393,397]"
    },
    {
      "src": "name: sorted_word_frequency [736,757]",
      "dest": "name: sorted_word_frequency [702,723]"
    },
    {
      "src": "trailer [284,286]",
      "dest": "trailer [321,323]"
    },
    {
      "src": "operator: = [262,263]",
      "dest": "operator: = [299,300]"
    },
    {
      "src": "string: '' [122,124]",
      "dest": "string: '' [133,135]"
    },
    {
      "src": "simple_stmt [252,287]",
      "dest": "simple_stmt [289,324]"
    },
    {
      "src": "file_input [0,757]",
      "dest": "file_input [0,745]"
    },
    {
      "src": "trailer [519,525]",
      "dest": "trailer [422,433]"
    },
    {
      "src": "name: x [691,692]",
      "dest": "name: x [595,596]"
    },
    {
      "src": "comp_if [156,185]",
      "dest": "comp_if [193,222]"
    },
    {
      "src": "atom_expr [264,286]",
      "dest": "atom_expr [301,323]"
    },
    {
      "src": "operator: = [704,705]",
      "dest": "operator: = [608,609]"
    },
    {
      "src": "name: word_frequency [339,353]",
      "dest": "name: word_frequency [376,390]"
    },
    {
      "src": "name: cleaned_string [105,119]",
      "dest": "name: cleaned_string [116,130]"
    },
    {
      "src": "name: split [279,284]",
      "dest": "name: split [316,321]"
    },
    {
      "src": "simple_stmt [105,187]",
      "dest": "simple_stmt [116,224]"
    },
    {
      "src": "atom_expr [130,139]",
      "dest": "atom_expr [141,150]"
    },
    {
      "src": "name: c [144,145]",
      "dest": "name: c [181,182]"
    },
    {
      "src": "arglist [653,709]",
      "dest": "arglist [557,613]"
    },
    {
      "src": "trailer [652,710]",
      "dest": "trailer [556,614]"
    },
    {
      "src": "trailer [645,711]",
      "dest": "trailer [549,615]"
    },
    {
      "src": "name: items [668,673]",
      "dest": "name: items [572,577]"
    },
    {
      "src": "or_test [159,185]",
      "dest": "or_test [196,222]"
    },
    {
      "src": "name: reverse [697,704]",
      "dest": "name: reverse [601,608]"
    },
    {
      "src": "simple_stmt [617,712]",
      "dest": "simple_stmt [521,616]"
    },
    {
      "src": "name: dict [641,645]",
      "dest": "name: dict [545,549]"
    },
    {
      "src": "trailer [168,170]",
      "dest": "trailer [205,207]"
    },
    {
      "src": "name: string [149,155]",
      "dest": "name: string [186,192]"
    },
    {
      "src": "operator: = [639,640]",
      "dest": "operator: = [543,544]"
    },
    {
      "src": "name: isspace [176,183]",
      "dest": "name: isspace [213,220]"
    },
    {
      "src": "name: cleaned_string [264,278]",
      "dest": "name: cleaned_string [301,315]"
    },
    {
      "src": "name: word [520,524]",
      "dest": "name: word_list [423,432]"
    }
  ],
  "actions": [
    {
      "action": "insert-tree",
      "tree": "param [41,46]",
      "parent": "parameters [40,59]",
      "at": 0
    },
    {
      "action": "insert-node",
      "tree": "simple_stmt [376,434]",
      "parent": "suite [60,741]",
      "at": 2
    },
    {
      "action": "insert-node",
      "tree": "simple_stmt [682,741]",
      "parent": "suite [60,741]",
      "at": 4
    },
    {
      "action": "update-node",
      "tree": "name: string [41,47]",
      "label": "string_list"
    },
    {
      "action": "insert-node",
      "tree": "expr_stmt [376,433]",
      "parent": "simple_stmt [376,434]",
      "at": 0
    },
    {
      "action": "move-tree",
      "tree": "return_stmt [729,757]",
      "parent": "simple_stmt [682,741]",
      "at": 0
    },
    {
      "action": "move-tree",
      "tree": "name: word_frequency [339,353]",
      "parent": "expr_stmt [376,433]",
      "at": 0
    },
    {
      "action": "move-tree",
      "tree": "operator: = [354,355]",
      "parent": "expr_stmt [376,433]",
      "at": 1
    },
    {
      "action": "insert-node",
      "tree": "atom_expr [393,433]",
      "parent": "expr_stmt [376,433]",
      "at": 2
    },
    {
      "action": "insert-node",
      "tree": "atom_expr [689,740]",
      "parent": "return_stmt [682,740]",
      "at": 0
    },
    {
      "action": "update-node",
      "tree": "name: word [371,375]",
      "label": "self"
    },
    {
      "action": "move-tree",
      "tree": "name: word [371,375]",
      "parent": "atom_expr [393,433]",
      "at": 0
    },
    {
      "action": "move-tree",
      "tree": "trailer [459,465]",
      "parent": "atom_expr [393,433]",
      "at": 1
    },
    {
      "action": "move-tree",
      "tree": "trailer [519,525]",
      "parent": "atom_expr [393,433]",
      "at": 2
    },
    {
      "action": "insert-node",
      "tree": "name: dict [689,693]",
      "parent": "atom_expr [689,740]",
      "at": 0
    },
    {
      "action": "insert-node",
      "tree": "trailer [693,740]",
      "parent": "atom_expr [689,740]",
      "at": 1
    },
    {
      "action": "update-node",
      "tree": "name: word [460,464]",
      "label": "calculate_word_frequency"
    },
    {
      "action": "update-node",
      "tree": "name: word [520,524]",
      "label": "word_list"
    },
    {
      "action": "insert-node",
      "tree": "atom_expr [694,739]",
      "parent": "trailer [693,740]",
      "at": 0
    },
    {
      "action": "insert-node",
      "tree": "sync_comp_for [151,222]",
      "parent": "argument [141,222]",
      "at": 1
    },
    {
      "action": "insert-node",
      "tree": "name: Counter [694,701]",
      "parent": "atom_expr [694,739]",
      "at": 0
    },
    {
      "action": "insert-node",
      "tree": "trailer [701,724]",
      "parent": "atom_expr [694,739]",
      "at": 1
    },
    {
      "action": "insert-tree",
      "tree": "trailer [724,736]",
      "parent": "atom_expr [694,739]",
      "at": 2
    },
    {
      "action": "insert-tree",
      "tree": "trailer [736,739]",
      "parent": "atom_expr [694,739]",
      "at": 3
    },
    {
      "action": "insert-node",
      "tree": "name: string [155,161]",
      "parent": "sync_comp_for [151,222]",
      "at": 0
    },
    {
      "action": "insert-node",
      "tree": "name: string_list [165,176]",
      "parent": "sync_comp_for [151,222]",
      "at": 1
    },
    {
      "action": "move-tree",
      "tree": "sync_comp_for [140,185]",
      "parent": "sync_comp_for [151,222]",
      "at": 2
    },
    {
      "action": "move-tree",
      "tree": "name: sorted_word_frequency [736,757]",
      "parent": "trailer [701,724]",
      "at": 0
    },
    {
      "action": "delete-tree",
      "tree": "atom [356,358]"
    },
    {
      "action": "delete-node",
      "tree": "expr_stmt [339,358]"
    },
    {
      "action": "delete-node",
      "tree": "simple_stmt [339,359]"
    },
    {
      "action": "delete-node",
      "tree": "name: word_list [379,388]"
    },
    {
      "action": "delete-tree",
      "tree": "comparison [405,427]"
    },
    {
      "action": "delete-node",
      "tree": "name: word_frequency [445,459]"
    },
    {
      "action": "delete-node",
      "tree": "atom_expr [445,465]"
    },
    {
      "action": "delete-node",
      "tree": "operator: += [466,468]"
    },
    {
      "action": "delete-node",
      "tree": "number: 1 [469,470]"
    },
    {
      "action": "delete-node",
      "tree": "expr_stmt [445,470]"
    },
    {
      "action": "delete-node",
      "tree": "simple_stmt [445,471]"
    },
    {
      "action": "delete-node",
      "tree": "suite [428,471]"
    },
    {
      "action": "delete-node",
      "tree": "name: word_frequency [505,519]"
    },
    {
      "action": "delete-node",
      "tree": "atom_expr [505,525]"
    },
    {
      "action": "delete-node",
      "tree": "operator: = [526,527]"
    },
    {
      "action": "delete-node",
      "tree": "number: 1 [528,529]"
    },
    {
      "action": "delete-node",
      "tree": "expr_stmt [505,529]"
    },
    {
      "action": "delete-node",
      "tree": "simple_stmt [505,530]"
    },
    {
      "action": "delete-node",
      "tree": "suite [488,530]"
    },
    {
      "action": "delete-node",
      "tree": "if_stmt [402,530]"
    },
    {
      "action": "delete-node",
      "tree": "suite [389,530]"
    },
    {
      "action": "delete-node",
      "tree": "for_stmt [367,530]"
    }
  ]
}