[
    {
        "action": "INS",
        "label": "simple_stmt",
        "inserted": "where_clause = ''\n",
        "deleted": "",
        "type": "Logic"
    },
    {
        "action": "INS",
        "label": "operator",
        "inserted": "=",
        "deleted": "",
        "type": "Logic"
    },
    {
        "action": "INS",
        "label": "name",
        "inserted": "where",
        "deleted": "",
        "type": "Logic"
    },
    {
        "action": "INS",
        "label": "string:",
        "inserted": "'WHERE '",
        "deleted": "",
        "type": "Logic"
    },
    {
        "action": "INS",
        "label": "operator",
        "inserted": "+",
        "deleted": "",
        "type": "Logic"
    },
    {
        "action": "INS",
        "label": "string:",
        "inserted": "' AND '",
        "deleted": "",
        "type": "Logic"
    },
    {
        "action": "INS",
        "label": "trailer",
        "inserted": ".join",
        "deleted": "",
        "type": "Logic"
    },
    {
        "action": "INS",
        "label": "sync_comp_for",
        "inserted": "for column, value in where.items()",
        "deleted": "",
        "type": "Logic"
    },
    {
        "action": "INS",
        "label": "fstring_expr",
        "inserted": "{column}",
        "deleted": "",
        "type": "Logic"
    },
    {
        "action": "INS",
        "label": "fstring_string",
        "inserted": "'",
        "deleted": "",
        "type": "Logic"
    },
    {
        "action": "MOV",
        "label": "fstring",
        "inserted": "f\"WHERE {condition}\"",
        "deleted": "f\"WHERE {condition}\"",
        "type": "Move"
    },
    {
        "action": "UPD",
        "label": "name",
        "inserted": "data",
        "deleted": "values",
        "type": "Refactoring"
    },
    {
        "action": "UPD",
        "label": "name",
        "inserted": "where",
        "deleted": "condition",
        "type": "Refactoring"
    },
    {
        "action": "UPD",
        "label": "name",
        "inserted": "data",
        "deleted": "values",
        "type": "Refactoring"
    },
    {
        "action": "UPD",
        "label": "fstring_string:",
        "inserted": " = '",
        "deleted": "WHERE ",
        "type": "Logic"
    },
    {
        "action": "UPD",
        "label": "name",
        "inserted": "value",
        "deleted": "condition",
        "type": "Refactoring"
    }
]