[
    {
        "action": "INS",
        "label": "simple_stmt",
        "inserted": "\"\"\"\n        Add one or several books to inventory which is sorted by book title.\n        :param title: str, the book title\n        :param quantity: int, default value is 1.\n        \"\"\"\n",
        "deleted": "",
        "type": "Documentation"
    },
    {
        "action": "INS",
        "label": "name",
        "inserted": "title",
        "deleted": "",
        "type": "Logic"
    },
    {
        "action": "INS",
        "label": "operator",
        "inserted": "=",
        "deleted": "",
        "type": "Logic"
    },
    {
        "action": "INS",
        "label": "number",
        "inserted": "1",
        "deleted": "",
        "type": "Logic"
    },
    {
        "action": "INS",
        "label": "name",
        "inserted": "self",
        "deleted": "",
        "type": "Logic"
    },
    {
        "action": "INS",
        "label": "trailer",
        "inserted": ".inventory",
        "deleted": "",
        "type": "Logic"
    },
    {
        "action": "INS",
        "label": "trailer",
        "inserted": "(quantity)",
        "deleted": "",
        "type": "Logic"
    },
    {
        "action": "INS",
        "label": "name",
        "inserted": "self",
        "deleted": "",
        "type": "Logic"
    },
    {
        "action": "INS",
        "label": "trailer",
        "inserted": ".inventory",
        "deleted": "",
        "type": "Logic"
    },
    {
        "action": "INS",
        "label": "operator",
        "inserted": "{",
        "deleted": "",
        "type": "Logic"
    },
    {
        "action": "INS",
        "label": "operator",
        "inserted": "}",
        "deleted": "",
        "type": "Logic"
    },
    {
        "action": "INS",
        "label": "string",
        "inserted": "'title'",
        "deleted": "",
        "type": "Logic"
    },
    {
        "action": "DEL",
        "label": "param",
        "inserted": "",
        "deleted": "*books",
        "type": "Method_Signature"
    },
    {
        "action": "MOV",
        "label": "operator",
        "inserted": "*",
        "deleted": "*",
        "type": "Move"
    },
    {
        "action": "MOV",
        "label": "name",
        "inserted": "books",
        "deleted": "books",
        "type": "Move"
    },
    {
        "action": "MOV",
        "label": "name",
        "inserted": "books",
        "deleted": "books",
        "type": "Move"
    },
    {
        "action": "MOV",
        "label": "name",
        "inserted": "inventory",
        "deleted": "inventory",
        "type": "Move"
    },
    {
        "action": "MOV",
        "label": "name",
        "inserted": "inventory",
        "deleted": "inventory",
        "type": "Move"
    },
    {
        "action": "MOV",
        "label": "name",
        "inserted": "book",
        "deleted": "book",
        "type": "Move"
    },
    {
        "action": "UPD",
        "label": "name",
        "inserted": "self",
        "deleted": "inventory",
        "type": "Refactoring"
    },
    {
        "action": "UPD",
        "label": "operator",
        "inserted": ",",
        "deleted": "*",
        "type": "Logic"
    },
    {
        "action": "UPD",
        "label": "name",
        "inserted": "quantity",
        "deleted": "books",
        "type": "Refactoring"
    },
    {
        "action": "UPD",
        "label": "name",
        "inserted": "_",
        "deleted": "book",
        "type": "Refactoring"
    },
    {
        "action": "UPD",
        "label": "name",
        "inserted": "range",
        "deleted": "books",
        "type": "Refactoring"
    },
    {
        "action": "UPD",
        "label": "name",
        "inserted": "title",
        "deleted": "book",
        "type": "Refactoring"
    }
]