{
  "matches": [
    {
      "src": "operator: { [295,296]",
      "dest": "operator: { [542,543]"
    },
    {
      "src": "fstring_expr [500,506]",
      "dest": "fstring_expr [747,753]"
    },
    {
      "src": "atom_expr [266,341]",
      "dest": "atom_expr [513,588]"
    },
    {
      "src": "operator: >= [189,191]",
      "dest": "operator: >= [427,429]"
    },
    {
      "src": "suite [19,538]",
      "dest": "suite [19,784]"
    },
    {
      "src": "operator: } [311,312]",
      "dest": "operator: } [558,559]"
    },
    {
      "src": "operator: = [135,136]",
      "dest": "operator: = [364,365]"
    },
    {
      "src": "fstring_expr [425,431]",
      "dest": "fstring_expr [672,678]"
    },
    {
      "src": "classdef [0,538]",
      "dest": "classdef [0,784]"
    },
    {
      "src": "simple_stmt [266,342]",
      "dest": "simple_stmt [513,589]"
    },
    {
      "src": "suite [71,538]",
      "dest": "suite [64,784]"
    },
    {
      "src": "operator: { [306,307]",
      "dest": "operator: { [553,554]"
    },
    {
      "src": "name: quantity [61,69]",
      "dest": "name: quantity [52,60]"
    },
    {
      "src": "name: shopping_list [40,53]",
      "dest": "name: self [40,44]"
    },
    {
      "src": "fstring [491,536]",
      "dest": "fstring [738,783]"
    },
    {
      "src": "comparison [172,200]",
      "dest": "comparison [410,438]"
    },
    {
      "src": "operator: } [430,431]",
      "dest": "operator: } [677,678]"
    },
    {
      "src": "parameters [39,70]",
      "dest": "parameters [39,63]"
    },
    {
      "src": "fstring [272,340]",
      "dest": "fstring [519,587]"
    },
    {
      "src": "operator: { [500,501]",
      "dest": "operator: { [747,748]"
    },
    {
      "src": "operator: } [505,506]",
      "dest": "operator: } [752,753]"
    },
    {
      "src": "fstring_expr [406,424]",
      "dest": "fstring_expr [653,671]"
    },
    {
      "src": "fstring_end: \" [456,457]",
      "dest": "fstring_end: \" [703,704]"
    },
    {
      "src": "fstring_string: (s) in the shopping list. [431,456]",
      "dest": "fstring_string: (s) in the shopping list. [678,703]"
    },
    {
      "src": "name: quantity [296,304]",
      "dest": "name: quantity [543,551]"
    },
    {
      "src": "name: quantity [192,200]",
      "dest": "name: quantity [430,438]"
    },
    {
      "src": "name: print [376,381]",
      "dest": "name: print [623,628]"
    },
    {
      "src": "name: item [55,59]",
      "dest": "name: item [46,50]"
    },
    {
      "src": "name: item [232,236]",
      "dest": "name: item [467,471]"
    },
    {
      "src": "operator: , [59,60]",
      "dest": "operator: , [50,51]"
    },
    {
      "src": "operator: { [425,426]",
      "dest": "operator: { [672,673]"
    },
    {
      "src": "name: item [426,430]",
      "dest": "name: item [673,677]"
    },
    {
      "src": "if_stmt [169,459]",
      "dest": "if_stmt [407,706]"
    },
    {
      "src": "simple_stmt [118,157]",
      "dest": "simple_stmt [347,395]"
    },
    {
      "src": "suite [472,538]",
      "dest": "suite [719,784]"
    },
    {
      "src": "operator: , [53,54]",
      "dest": "operator: , [44,45]"
    },
    {
      "src": "trailer [271,341]",
      "dest": "trailer [518,588]"
    },
    {
      "src": "fstring_end: \" [339,340]",
      "dest": "fstring_end: \" [586,587]"
    },
    {
      "src": "name: item [307,311]",
      "dest": "name: item [554,558]"
    },
    {
      "src": "suite [201,342]",
      "dest": "suite [439,589]"
    },
    {
      "src": "funcdef [24,538]",
      "dest": "funcdef [24,784]"
    },
    {
      "src": "name: item [83,87]",
      "dest": "name: item [315,319]"
    },
    {
      "src": "fstring_string:   [424,425]",
      "dest": "fstring_string:   [671,672]"
    },
    {
      "src": "trailer [381,458]",
      "dest": "trailer [628,705]"
    },
    {
      "src": "atom_expr [485,537]",
      "dest": "atom_expr [732,784]"
    },
    {
      "src": "operator: } [304,305]",
      "dest": "operator: } [551,552]"
    },
    {
      "src": "operator: { [406,407]",
      "dest": "operator: { [653,654]"
    },
    {
      "src": "name: print [266,271]",
      "dest": "name: print [513,518]"
    },
    {
      "src": "fstring_end: \" [535,536]",
      "dest": "fstring_end: \" [782,783]"
    },
    {
      "src": "expr_stmt [218,249]",
      "dest": "expr_stmt [456,496]"
    },
    {
      "src": "suite [359,459]",
      "dest": "suite [606,706]"
    },
    {
      "src": "fstring_string: Error:  [493,500]",
      "dest": "fstring_string: Error:  [740,747]"
    },
    {
      "src": "fstring_string: Error: There are only  [384,406]",
      "dest": "fstring_string: Error: There are only  [631,653]"
    },
    {
      "src": "operator: } [423,424]",
      "dest": "operator: } [670,671]"
    },
    {
      "src": "comparison [83,104]",
      "dest": "comparison [315,333]"
    },
    {
      "src": "name: current_quantity [172,188]",
      "dest": "name: current_quantity [410,426]"
    },
    {
      "src": "expr_stmt [118,156]",
      "dest": "expr_stmt [347,394]"
    },
    {
      "src": "name: shopping_list [137,150]",
      "dest": "name: self [366,370]"
    },
    {
      "src": "fstring_expr [306,312]",
      "dest": "fstring_expr [553,559]"
    },
    {
      "src": "fstring_start: f\" [491,493]",
      "dest": "fstring_start: f\" [738,740]"
    },
    {
      "src": "name: item [151,155]",
      "dest": "name: item [377,381]"
    },
    {
      "src": "param [55,60]",
      "dest": "param [46,51]"
    },
    {
      "src": "atom_expr [218,237]",
      "dest": "atom_expr [456,484]"
    },
    {
      "src": "name: print [485,490]",
      "dest": "name: print [732,737]"
    },
    {
      "src": "name: ShoppingCart [6,18]",
      "dest": "name: ShoppingCart [6,18]"
    },
    {
      "src": "file_input [0,542]",
      "dest": "file_input [0,784]"
    },
    {
      "src": "suite [105,459]",
      "dest": "suite [334,706]"
    },
    {
      "src": "trailer [490,537]",
      "dest": "trailer [737,784]"
    },
    {
      "src": "simple_stmt [218,250]",
      "dest": "simple_stmt [456,497]"
    },
    {
      "src": "fstring_string: (s) from the shopping list. [312,339]",
      "dest": "fstring_string: (s) from the shopping list. [559,586]"
    },
    {
      "src": "operator: -= [238,240]",
      "dest": "operator: -= [485,487]"
    },
    {
      "src": "fstring_string: Successfully removed  [274,295]",
      "dest": "fstring_string: Successfully removed  [521,542]"
    },
    {
      "src": "fstring_string:  is not in the shopping list. [506,535]",
      "dest": "fstring_string:  is not in the shopping list. [753,782]"
    },
    {
      "src": "trailer [231,237]",
      "dest": "trailer [466,472]"
    },
    {
      "src": "fstring_expr [295,305]",
      "dest": "fstring_expr [542,552]"
    },
    {
      "src": "fstring_string:   [305,306]",
      "dest": "fstring_string:   [552,553]"
    },
    {
      "src": "name: item [501,505]",
      "dest": "name: item [748,752]"
    },
    {
      "src": "param [40,54]",
      "dest": "param [40,45]"
    },
    {
      "src": "fstring_start: f\" [382,384]",
      "dest": "fstring_start: f\" [629,631]"
    },
    {
      "src": "name: current_quantity [118,134]",
      "dest": "name: current_quantity [347,363]"
    },
    {
      "src": "fstring [382,457]",
      "dest": "fstring [629,704]"
    },
    {
      "src": "atom_expr [376,458]",
      "dest": "atom_expr [623,705]"
    },
    {
      "src": "name: current_quantity [407,423]",
      "dest": "name: current_quantity [654,670]"
    },
    {
      "src": "atom_expr [137,156]",
      "dest": "atom_expr [366,394]"
    },
    {
      "src": "fstring_start: f\" [272,274]",
      "dest": "fstring_start: f\" [519,521]"
    },
    {
      "src": "name: quantity [241,249]",
      "dest": "name: quantity [488,496]"
    },
    {
      "src": "if_stmt [80,538]",
      "dest": "if_stmt [312,784]"
    },
    {
      "src": "param [61,69]",
      "dest": "param [52,62]"
    },
    {
      "src": "simple_stmt [376,459]",
      "dest": "simple_stmt [623,706]"
    },
    {
      "src": "trailer [150,156]",
      "dest": "trailer [376,382]"
    },
    {
      "src": "name: remove_item [28,39]",
      "dest": "name: remove_item [28,39]"
    },
    {
      "src": "name: shopping_list [91,104]",
      "dest": "name: self [323,327]"
    },
    {
      "src": "name: shopping_list [218,231]",
      "dest": "name: self [456,460]"
    }
  ],
  "actions": [
    {
      "action": "insert-tree",
      "tree": "simple_stmt [73,304]",
      "parent": "suite [64,784]",
      "at": 0
    },
    {
      "action": "update-node",
      "tree": "name: shopping_list [40,53]",
      "label": "self"
    },
    {
      "action": "insert-node",
      "tree": "operator: = [60,61]",
      "parent": "param [52,62]",
      "at": 1
    },
    {
      "action": "insert-node",
      "tree": "number: 1 [61,62]",
      "parent": "param [52,62]",
      "at": 2
    },
    {
      "action": "insert-node",
      "tree": "atom_expr [323,333]",
      "parent": "comparison [315,333]",
      "at": 1
    },
    {
      "action": "move-tree",
      "tree": "atom_expr [485,537]",
      "parent": "suite [719,784]",
      "at": 0
    },
    {
      "action": "update-node",
      "tree": "name: shopping_list [91,104]",
      "label": "self"
    },
    {
      "action": "move-tree",
      "tree": "name: shopping_list [91,104]",
      "parent": "atom_expr [323,333]",
      "at": 0
    },
    {
      "action": "insert-tree",
      "tree": "trailer [327,333]",
      "parent": "atom_expr [323,333]",
      "at": 1
    },
    {
      "action": "update-node",
      "tree": "name: shopping_list [137,150]",
      "label": "self"
    },
    {
      "action": "insert-tree",
      "tree": "trailer [370,376]",
      "parent": "atom_expr [366,394]",
      "at": 1
    },
    {
      "action": "insert-tree",
      "tree": "trailer [382,394]",
      "parent": "atom_expr [366,394]",
      "at": 3
    },
    {
      "action": "update-node",
      "tree": "name: shopping_list [218,231]",
      "label": "self"
    },
    {
      "action": "insert-tree",
      "tree": "trailer [460,466]",
      "parent": "atom_expr [456,484]",
      "at": 1
    },
    {
      "action": "insert-tree",
      "tree": "trailer [472,484]",
      "parent": "atom_expr [456,484]",
      "at": 3
    },
    {
      "action": "delete-node",
      "tree": "simple_stmt [485,538]"
    }
  ]
}