[
    {
        "action": "INS",
        "label": "param",
        "inserted": "self,",
        "deleted": "",
        "type": "Method_Signature"
    },
    {
        "action": "INS",
        "label": "simple_stmt",
        "inserted": "\"\"\"\n        Use Image util in PIL to open a image\n        :param image_path: str, path of image that is to be\n        \"\"\"\n",
        "deleted": "",
        "type": "Documentation"
    },
    {
        "action": "INS",
        "label": "name",
        "inserted": "self",
        "deleted": "",
        "type": "Logic"
    },
    {
        "action": "INS",
        "label": "trailer",
        "inserted": ".image",
        "deleted": "",
        "type": "Logic"
    },
    {
        "action": "DEL",
        "label": "simple_stmt",
        "inserted": "",
        "deleted": "image = Image.open(image_path)\n",
        "type": "Logic"
    },
    {
        "action": "DEL",
        "label": "return_stmt",
        "inserted": "",
        "deleted": "return image",
        "type": "Logic"
    },
    {
        "action": "MOV",
        "label": "name",
        "inserted": "image",
        "deleted": "image",
        "type": "Move"
    }
]